
    {
	"criteria": {
    "has_item": {
      "trigger": "minecraft:inventory_changed",
      "conditions": {
        "items": [
          {
            "items": [
              "minecraft:packed_ice"
            ]
          }
        ]
      }
    }
  },
	"requirements": [
		[
			"has_item"
		]
	],
	"rewards": {
		"recipes": [
			"ctft:packed_ice_sword_from_crafting",
			"ctft:packed_ice_pickaxe_from_crafting",
			"ctft:packed_ice_axe_from_crafting",
			"ctft:packed_ice_shovel_from_crafting",
			"ctft:packed_ice_hoe_from_crafting",
			"ctft:packed_ice_shield_from_crafting",
			"ctft:packed_ice_fishing_rod_from_crafting",
			"ctft:packed_ice_compass_from_crafting",
			"ctft:packed_ice_clock_from_crafting",
			"ctft:packed_ice_helmet_from_crafting",
			"ctft:packed_ice_chestplate_from_crafting",
			"ctft:packed_ice_leggings_from_crafting",
			"ctft:packed_ice_boots_from_crafting",
			"ctft:packed_ice_shears_from_crafting",
			"ctft:packed_ice_horse_armor_from_crafting",
			"ctft:packed_ice_bow_from_crafting",
			"ctft:packed_ice_crossbow_from_crafting",
			"ctft:packed_ice_block_from_material",
			"ctft:packed_ice_material_from_block",
			"ctft:packed_ice_stairs_from_crafting",
			"ctft:packed_ice_slab_from_crafting",
			"ctft:packed_ice_glass_pane_from_crafting",
			"ctft:packed_ice_pane_from_crafting",
			"ctft:packed_ice_glass_from_smelting",
			"ctft:packed_ice_stairs_from_stonecutter",
			"ctft:packed_ice_slab_from_stonecutter",
			"ctft:packed_ice_wall_from_stonecutter",
			"ctft:packed_ice_lever_from_crafting",
			"ctft:packed_ice_button_from_crafting",
			"ctft:packed_ice_pressure_plate_from_crafting",
			"ctft:packed_ice_fence_gate_from_crafting"
		]
	}
}