
    {
	"criteria": {
    "has_item": {
      "trigger": "minecraft:inventory_changed",
      "conditions": {
        "items": [
          {
            "items": [
              "minecraft:shulker_box"
            ]
          }
        ]
      }
    }
  },
	"requirements": [
		[
			"has_item"
		]
	],
	"rewards": {
		"recipes": [
			"ctft:shulker_box_sword",
			"ctft:shulker_box_pickaxe",
			"ctft:shulker_box_axe",
			"ctft:shulker_box_shovel",
			"ctft:shulker_box_hoe",
			"ctft:shulker_box_shield",
			"ctft:shulker_box_fishing_rod",
			"ctft:shulker_box_compass",
			"ctft:shulker_box_clock",
			"ctft:shulker_box_helmet",
			"ctft:shulker_box_chestplate",
			"ctft:shulker_box_leggings",
			"ctft:shulker_box_boots",
			"ctft:shulker_box_shears",
			"ctft:shulker_box_horse_armor",
			"ctft:shulker_box_bow",
			"ctft:shulker_box_crossbow"
		]
	}
}