
    {
	"criteria": {
    "has_item": {
      "trigger": "minecraft:inventory_changed",
      "conditions": {
        "items": [
          {
            "items": [
              "minecraft:wooden_sword"
            ]
          }
        ]
      }
    }
  },
	"requirements": [
		[
			"has_item"
		]
	],
	"rewards": {
		"recipes": [
			"ctft:wooden_sword_sword",
			"ctft:wooden_sword_pickaxe",
			"ctft:wooden_sword_axe",
			"ctft:wooden_sword_shovel",
			"ctft:wooden_sword_hoe",
			"ctft:wooden_sword_shield",
			"ctft:wooden_sword_fishing_rod",
			"ctft:wooden_sword_compass",
			"ctft:wooden_sword_clock",
			"ctft:wooden_sword_helmet",
			"ctft:wooden_sword_chestplate",
			"ctft:wooden_sword_leggings",
			"ctft:wooden_sword_boots",
			"ctft:wooden_sword_shears",
			"ctft:wooden_sword_horse_armor",
			"ctft:wooden_sword_bow"
		]
	}
}