{
	"credit": "made by chyzman",
	"parent": "block/block",
	"textures": {
		"0": "ctft:blocks/beacon_compressed"
	},
	"elements": [
		{
			"from": [0, 0, 0],
			"to": [16, 16, 16],
			"faces": {
				"north": {"uv": [0, 0, 12, 12], "texture": "#0", "cullface": "north"},
				"east": {"uv": [0, 0, 12, 12], "texture": "#0", "cullface": "east"},
				"south": {"uv": [0, 0, 12, 12], "texture": "#0", "cullface": "south"},
				"west": {"uv": [0, 0, 12, 12], "texture": "#0", "cullface": "west"},
				"up": {"uv": [0, 0, 12, 12], "texture": "#0", "cullface": "up"},
				"down": {"uv": [0, 0, 12, 12], "texture": "#0", "cullface": "down"}
			}
		}
	]
}